rocratepcc/__init__.py
rocratepcc/py/__init__.py
rocratepcc/py/fable_modules/arctrl_contract/__init__.py
rocratepcc/py/fable_modules/arctrl_contract/arc.py
rocratepcc/py/fable_modules/arctrl_contract/arc_assay.py
rocratepcc/py/fable_modules/arctrl_contract/arc_investigation.py
rocratepcc/py/fable_modules/arctrl_contract/arc_run.py
rocratepcc/py/fable_modules/arctrl_contract/arc_study.py
rocratepcc/py/fable_modules/arctrl_contract/arc_workflow.py
rocratepcc/py/fable_modules/arctrl_contract/contract.py
rocratepcc/py/fable_modules/arctrl_contract/datamap.py
rocratepcc/py/fable_modules/arctrl_contract/git.py
rocratepcc/py/fable_modules/arctrl_contract/license.py
rocratepcc/py/fable_modules/arctrl_contract/validation_packages_config.py
rocratepcc/py/fable_modules/arctrl_core/__init__.py
rocratepcc/py/fable_modules/arctrl_core/arc_types.py
rocratepcc/py/fable_modules/arctrl_core/comment.py
rocratepcc/py/fable_modules/arctrl_core/comment_list.py
rocratepcc/py/fable_modules/arctrl_core/conversion.py
rocratepcc/py/fable_modules/arctrl_core/data.py
rocratepcc/py/fable_modules/arctrl_core/data_context.py
rocratepcc/py/fable_modules/arctrl_core/data_file.py
rocratepcc/py/fable_modules/arctrl_core/data_map.py
rocratepcc/py/fable_modules/arctrl_core/Helper/__init__.py
rocratepcc/py/fable_modules/arctrl_core/Helper/collections_.py
rocratepcc/py/fable_modules/arctrl_core/Helper/date_time.py
rocratepcc/py/fable_modules/arctrl_core/Helper/hash_codes.py
rocratepcc/py/fable_modules/arctrl_core/Helper/identifier.py
rocratepcc/py/fable_modules/arctrl_core/Helper/orcid.py
rocratepcc/py/fable_modules/arctrl_core/Helper/printer.py
rocratepcc/py/fable_modules/arctrl_core/Helper/regex.py
rocratepcc/py/fable_modules/arctrl_core/Helper/sem_ver.py
rocratepcc/py/fable_modules/arctrl_core/Helper/url.py
rocratepcc/py/fable_modules/arctrl_core/identifier_setters.py
rocratepcc/py/fable_modules/arctrl_core/iproperty_value.py
rocratepcc/py/fable_modules/arctrl_core/ontology_annotation.py
rocratepcc-0.0.3.dist-info/licenses/LICENSE
rocratepcc-0.0.3.dist-info/METADATA
rocratepcc-0.0.3.dist-info/WHEEL
rocratepcc-0.0.3.dist-info/RECORD
