Metadata-Version: 2.4
Name: rocratepcc
Version: 0.0.3
Summary: Polyglot library (.NET, Python, Javascript) for creation of RO-Crate Profile Crates.
License-File: LICENSE
Keywords: ro-crate,profile crate
Author: Heinrich Lukas Weil
Author-email: weil@rptu.de
Requires-Python: >=3.11
Classifier: Programming Language :: Python :: 3
Classifier: Programming Language :: Python :: 3.11
Classifier: Programming Language :: Python :: 3.12
Classifier: Programming Language :: Python :: 3.13
Classifier: Programming Language :: Python :: 3.14
Requires-Dist: arctrl (>=3.0.0b11,<4)
Project-URL: Repository, https://github.com/nfdi4plants/ROCratePCC
